{"custom":{"name":"D50_3834_2504","file":"D50_3834_2504.jpg","box":"Loreley 2025","featured":{"title":"Remaining Photos from 2025","slug":"Remaining-Photos-from-2025"},"links":[{"site":"pixelfed","url":""},{"site":"flickr","url":""},{"site":"vernissage","url":""}]},"ApplicationRecordVersion":"\u0000\u0004","ObjectName":"Witchcraft","Keywords":["2025","kristofz"],"DateCreated":"2025-04-20T11:17:16.61","TimeCreated":"111716","DigitalCreationDate":"20250420","DigitalCreationTime":"111716","Byline":"Kristof Zerbe","City":"Bornich","State":"Rhineland-Palatinate","CountryCode":"DE","Country":"Germany","CopyrightNotice":"2025","CreatorTool":"Adobe Photoshop Lightroom Classic 15.1 (Windows)","CreateDate":"2025-04-20T09:17:16.000Z","ModifyDate":"2026-01-11T13:14:05.000Z","MetadataDate":"2026-01-11T14:14:05+01:00","Rating":5,"Label":"Grün","format":"image/jpeg","creator":"Kristof Zerbe","title":{"lang":"x-default","value":"Witchcraft"},"rights":{"lang":"x-default","value":2025},"subject":[2025,"kristofz"],"SerialNumber":"6067053","LensInfo":[18,400,3.5,6.3],"Lens":"TAMRON 18-400mm F3.5-6.3 Di II VC HLD B028N","LensID":224,"ImageNumber":23969,"ApproximateFocusDistance":"4294967295/1","DistortionCorrectionAlreadyApplied":true,"LateralChromaticAberrationCorrectionAlreadyApplied":true,"VignetteCorrectionAlreadyApplied":true,"LensModel":"TAMRON 18-400mm F3.5-6.3 Di II VC HLD B028N","LabelColor":"green","DocumentID":"xmp.did:69ef7d95-7c45-fa45-a683-132296e5fdff","PreservedFileName":"D50_3834.NEF","OriginalDocumentID":"A25E8A2B37792EE6A8F8B00263388FE8","InstanceID":"xmp.iid:69ef7d95-7c45-fa45-a683-132296e5fdff","History":[{"action":"derived","parameters":"converted from image/x-nikon-nef to image/jpeg, saved to new location"},{"action":"saved","instanceID":"xmp.iid:69ef7d95-7c45-fa45-a683-132296e5fdff","when":"2026-01-11T14:14:05+01:00","softwareAgent":"Adobe Photoshop Lightroom Classic 15.1 (Windows)","changed":"/"}],"DerivedFrom":{"documentID":"A25E8A2B37792EE6A8F8B00263388FE8","originalDocumentID":"A25E8A2B37792EE6A8F8B00263388FE8"},"Marked":true,"WebStatement":"https://creativecommons.org/licenses/by-sa/4.0/","UsageTerms":{"lang":"x-default","value":"CC BY-SA 4.0"},"pick":0,"CreatorContactInfo":{"CiAdrCity":"Wiesbaden","CiUrlWork":"https://kiko.io"},"RawFileName":"D50_3834_2504.NEF","Version":18.1,"CompatibleVersion":251920384,"ProcessVersion":15.4,"WhiteBalance":"Auto","Temperature":3973,"Tint":7,"Exposure2012":0.34,"Contrast2012":87,"Highlights2012":-67,"Shadows2012":-100,"Whites2012":-61,"Blacks2012":43,"Texture":100,"Clarity2012":100,"Dehaze":25,"Vibrance":40,"Saturation":"Normal","ParametricShadows":0,"ParametricDarks":-29,"ParametricLights":27,"ParametricHighlights":-30,"ParametricShadowSplit":25,"ParametricMidtoneSplit":50,"ParametricHighlightSplit":75,"Sharpness":"Normal","SharpenRadius":2,"SharpenDetail":86,"SharpenEdgeMasking":18,"LuminanceSmoothing":71,"LuminanceNoiseReductionDetail":36,"LuminanceNoiseReductionContrast":0,"ColorNoiseReduction":51,"ColorNoiseReductionDetail":50,"ColorNoiseReductionSmoothness":50,"HueAdjustmentRed":0,"HueAdjustmentOrange":0,"HueAdjustmentYellow":0,"HueAdjustmentGreen":0,"HueAdjustmentAqua":0,"HueAdjustmentBlue":0,"HueAdjustmentPurple":0,"HueAdjustmentMagenta":0,"SaturationAdjustmentRed":0,"SaturationAdjustmentOrange":43,"SaturationAdjustmentYellow":-22,"SaturationAdjustmentGreen":0,"SaturationAdjustmentAqua":0,"SaturationAdjustmentBlue":0,"SaturationAdjustmentPurple":0,"SaturationAdjustmentMagenta":0,"LuminanceAdjustmentRed":0,"LuminanceAdjustmentOrange":0,"LuminanceAdjustmentYellow":0,"LuminanceAdjustmentGreen":0,"LuminanceAdjustmentAqua":0,"LuminanceAdjustmentBlue":0,"LuminanceAdjustmentPurple":0,"LuminanceAdjustmentMagenta":0,"SplitToningShadowHue":312,"SplitToningShadowSaturation":21,"SplitToningHighlightHue":63,"SplitToningHighlightSaturation":63,"SplitToningBalance":2,"ColorGradeMidtoneHue":0,"ColorGradeMidtoneSat":0,"ColorGradeShadowLum":0,"ColorGradeMidtoneLum":0,"ColorGradeHighlightLum":0,"ColorGradeBlending":100,"ColorGradeGlobalHue":0,"ColorGradeGlobalSat":0,"ColorGradeGlobalLum":0,"AutoLateralCA":1,"LensProfileEnable":1,"LensManualDistortionAmount":0,"VignetteAmount":0,"DefringePurpleAmount":0,"DefringePurpleHueLo":30,"DefringePurpleHueHi":70,"DefringeGreenAmount":0,"DefringeGreenHueLo":40,"DefringeGreenHueHi":60,"PerspectiveUpright":0,"PerspectiveVertical":0,"PerspectiveHorizontal":0,"PerspectiveRotate":0,"PerspectiveAspect":0,"PerspectiveScale":100,"PerspectiveX":0,"PerspectiveY":0,"GrainAmount":0,"PostCropVignetteAmount":-63,"PostCropVignetteMidpoint":50,"PostCropVignetteFeather":52,"PostCropVignetteRoundness":0,"PostCropVignetteStyle":1,"PostCropVignetteHighlightContrast":52,"ShadowTint":0,"RedHue":0,"RedSaturation":0,"GreenHue":0,"GreenSaturation":0,"BlueHue":0,"BlueSaturation":0,"HDREditMode":0,"HDRMaxValue":4,"CurveRefineSaturation":100,"OverrideLookVignette":true,"ToneCurveName2012":"Custom","CameraProfile":"Adobe Standard","CameraProfileDigest":"ABB0410514417CFA55F22BBA7035E8AB","LensProfileSetup":"LensDefaults","LensProfileName":"Adobe (TAMRON 18-400mm F3.5-6.3 Di II VC HLD B028N, NIKON CORPORATION)","LensProfileFilename":"NIKON CORPORATION (TAMRON 18-400mm F3.5-6.3 DiII VC HLD B028N) - RAW.lcp","LensProfileDigest":"D225EFB6E890637B304B00CCCC1E2448","LensProfileIsEmbedded":false,"LensProfileDistortionScale":100,"LensProfileVignettingScale":100,"HasSettings":true,"CropTop":0.055516,"CropLeft":0,"CropBottom":0.933096,"CropRight":0.875711,"CropAngle":0,"CropConstrainToWarp":0,"CropConstrainToUnitSquare":1,"HasCrop":true,"AlreadyApplied":true,"ToneCurvePV2012":["0, 0","129, 139","255, 255"],"ToneCurvePV2012Red":["0, 0","255, 255"],"ToneCurvePV2012Green":["0, 0","255, 255"],"ToneCurvePV2012Blue":["0, 0","255, 255"],"PointColors":"-1.000000, -1.000000, -1.000000, -1.000000, -1.000000, -1.000000, -1.000000, -1.000000, -1.000000, -1.000000, -1.000000, -1.000000, -1.000000, -1.000000, -1.000000, -1.000000, -1.000000, -1.000000, -1.000000","ColorVariance":-50,"RetouchAreas":[{"SpotType":"heal_patchmatch","SourceState":"sourceAutoComputed","Opacity":1,"Seed":2,"IngestInfo":"CA58001CC64A0929EA74368B26F67579","pm_patch_variations":[null,null],"Masks":{"What":"Mask/Paint","MaskActive":true,"MaskBlendMode":0,"MaskInverted":false,"MaskSyncID":"A6E70E0C7EE0284CBCC0BCFB031AAC63","MaskValue":1,"Radius":0.015556,"Flow":1,"CenterWeight":1,"Dabs":["r 0.015349","d 0.687285 0.051721","r 0.015342","d 0.686408 0.056191","r 0.015335","d 0.685935 0.060781","r 0.015328","d 0.685591 0.065390","r 0.015321","d 0.685472 0.070013","r 0.015315","d 0.685404 0.074633","r 0.015309","d 0.685359 0.079250","r 0.015304","d 0.686121 0.083689","r 0.015299","d 0.686828 0.088148","r 0.015295","d 0.687714 0.092526","r 0.015291","d 0.688859 0.096753","r 0.015287","d 0.690023 0.100966","r 0.015283","d 0.690861 0.105361","r 0.015278","d 0.691698 0.109754","r 0.015274","d 0.692508 0.114157","r 0.015270","d 0.693345 0.118547","r 0.015266","d 0.694100 0.122970","r 0.015263","d 0.695345 0.127117","r 0.015259","d 0.696314 0.131434","r 0.015255","d 0.696966 0.135892","r 0.015251","d 0.697813 0.140268","r 0.015248","d 0.698919 0.144501","r 0.015246","d 0.700510 0.148353","r 0.015243","d 0.701685 0.152540","r 0.015240","d 0.702928 0.156677","r 0.015238","d 0.704172 0.160814","r 0.015234","d 0.705192 0.165091","r 0.015231","d 0.706072 0.169439","r 0.015230","d 0.707921 0.173013","d 0.709843 0.176496","r 0.015226","d 0.710358 0.180982"]}},{"SpotType":"heal_patchmatch","SourceState":"sourceAutoComputed","Opacity":1,"Seed":1,"IngestInfo":"6B7DE52AEE31E0B3DC94FA4E5C96B0C9","pm_patch_variations":[null,null],"Masks":{"What":"Mask/Paint","MaskActive":true,"MaskBlendMode":0,"MaskInverted":false,"MaskSyncID":"31538E6F50F16741B45F489626E05F89","MaskValue":1,"Radius":0.004107,"Flow":1,"CenterWeight":1,"Dabs":["r 0.004017","d 0.758314 0.714913","r 0.004018","d 0.759122 0.714923","d 0.759930 0.714933","d 0.760738 0.714944","r 0.004019","d 0.761546 0.714954","d 0.762355 0.714964","r 0.004020","d 0.763163 0.714975","d 0.763972 0.714985","d 0.764781 0.714996","r 0.004021","d 0.765590 0.715007","d 0.766399 0.715017"]}},{"SpotType":"heal_patchmatch","SourceState":"sourceAutoComputed","Opacity":1,"Seed":1,"IngestInfo":"3CF8D36FED782332041F28415252710B","pm_patch_variations":[null,null],"Masks":{"What":"Mask/Paint","MaskActive":true,"MaskBlendMode":0,"MaskInverted":false,"MaskSyncID":"2921AFC712B3CA4DA128465952728D55","MaskValue":1,"Radius":0.016732,"Flow":1,"CenterWeight":1,"Dabs":["r 0.016269","d 0.745383 0.524636","r 0.016273","d 0.747648 0.528144","r 0.016278","d 0.749914 0.531654","r 0.016282","d 0.752181 0.535165","r 0.016287","d 0.754405 0.538740","r 0.016292","d 0.756629 0.542316","r 0.016297","d 0.758888 0.545847","r 0.016301","d 0.761149 0.549379","r 0.016307","d 0.763411 0.552912","r 0.016312","d 0.765674 0.556447","r 0.016316","d 0.767657 0.560333","r 0.016321","d 0.769641 0.564220","r 0.016325","d 0.770992 0.568659","r 0.016329","d 0.772345 0.573098","r 0.016333","d 0.774072 0.577250","r 0.016338","d 0.775800 0.581404","r 0.016343","d 0.777693 0.585400","r 0.016348","d 0.779589 0.589399","r 0.016353","d 0.781410 0.593472","r 0.016358","d 0.783234 0.597548","r 0.016364","d 0.785058 0.601625","r 0.016368","d 0.786347 0.606121","r 0.016372","d 0.787637 0.610619","r 0.016377","d 0.788704 0.615241","r 0.016381","d 0.789773 0.619864","r 0.016385","d 0.790990 0.624411","r 0.016390","d 0.792208 0.628960","r 0.016395","d 0.793427 0.633510","r 0.016401","d 0.795361 0.637499","r 0.016407","d 0.797297 0.641490","r 0.016413","d 0.799235 0.645483","r 0.016420","d 0.801123 0.649530","r 0.016425","d 0.802504 0.653995","r 0.016430","d 0.803886 0.658461","r 0.016435","d 0.804936 0.663116","r 0.016440","d 0.805988 0.667772","r 0.016446","d 0.807040 0.672430","r 0.016452","d 0.808463 0.676881"]}},{"SpotType":"heal_patchmatch","SourceState":"sourceAutoComputed","Opacity":1,"Seed":1,"IngestInfo":"F00C9C91228EFCBDE9E29E0528FA041A","pm_patch_variations":[null,null],"Masks":{"What":"Mask/Paint","MaskActive":true,"MaskBlendMode":0,"MaskInverted":false,"MaskSyncID":"CCE00E6361E96A49B44B5932E0974022","MaskValue":1,"Radius":0.016732,"Flow":1,"CenterWeight":1,"Dabs":["r 0.016444","d 0.772373 0.772213"]}},{"SpotType":"heal_patchmatch","SourceState":"sourceAutoComputed","Opacity":1,"Seed":1,"IngestInfo":"7311B5E119A0B7FF86035DA2640A1A3C","pm_patch_variations":[null,null],"Masks":{"What":"Mask/Paint","MaskActive":true,"MaskBlendMode":0,"MaskInverted":false,"MaskSyncID":"ED047E93E8068C44AFE643919F5A6024","MaskValue":1,"Radius":0.004107,"Flow":1,"CenterWeight":1,"Dabs":["r 0.004013","d 0.472720 0.070857","d 0.472721 0.072072","r 0.004012","d 0.472722 0.073286","d 0.473177 0.074285","r 0.004011","d 0.473631 0.075284","d 0.474085 0.076283","d 0.474539 0.077282","r 0.004010","d 0.475084 0.078168","d 0.475629 0.079054","d 0.476174 0.079940","r 0.004009","d 0.476642 0.080922","d 0.477111 0.081905","d 0.477651 0.082797","r 0.004008","d 0.478294 0.083512","d 0.478937 0.084227"]}},{"SpotType":"heal_patchmatch","SourceState":"sourceAutoComputed","Opacity":1,"Seed":1,"IngestInfo":"D7066E665356C2EEBD9A35C3B404CB54","pm_patch_variations":[null,null],"Masks":{"What":"Mask/Paint","MaskActive":true,"MaskBlendMode":0,"MaskInverted":false,"MaskSyncID":"FF63C6BC1F38D7478D7E8E0CB46519E8","MaskValue":1,"Radius":0.004107,"Flow":1,"CenterWeight":1,"Dabs":["r 0.003973","d 0.403100 0.243355","d 0.402393 0.243885","d 0.401743 0.244562","d 0.401093 0.245239","d 0.400444 0.245916","d 0.399794 0.246593","d 0.399145 0.247270","d 0.398495 0.247947","d 0.397893 0.248716"]}},{"SpotType":"heal_patchmatch","SourceState":"sourceAutoComputed","Opacity":1,"Seed":1,"IngestInfo":"1230C5172EB38FCBF7B2CC8649FA384F","pm_patch_variations":[null,null],"Masks":{"What":"Mask/Paint","MaskActive":true,"MaskBlendMode":0,"MaskInverted":false,"MaskSyncID":"58AB4BA8003AFF4584D29D7F4B4CB59D","MaskValue":1,"Radius":0.004107,"Flow":1,"CenterWeight":1,"Dabs":["r 0.004004","d 0.427044 0.110318","d 0.427179 0.111512","r 0.004003","d 0.427313 0.112706","d 0.427447 0.113899","r 0.004002","d 0.427688 0.115054","d 0.427897 0.116223","d 0.428107 0.117391","r 0.004001","d 0.428316 0.118559","d 0.428569 0.119708","r 0.004000","d 0.428636 0.120912","d 0.428704 0.122117","d 0.429045 0.123212","r 0.003999","d 0.429385 0.124307","d 0.429664 0.125441","d 0.429942 0.126575"]}},{"SpotType":"heal_patchmatch","SourceState":"sourceAutoComputed","Opacity":1,"Seed":1,"IngestInfo":"FD8E13FCE0EC6B866033B41748FA62E9","pm_patch_variations":[null,null],"Masks":{"What":"Mask/Paint","MaskActive":true,"MaskBlendMode":0,"MaskInverted":false,"MaskSyncID":"ED79F5C42C38A644842A9AE535F80FD8","MaskValue":1,"Radius":0.004107,"Flow":1,"CenterWeight":1,"Dabs":["r 0.003999","d 0.501263 0.111833"]}},{"SpotType":"heal_patchmatch","SourceState":"sourceAutoComputed","Opacity":1,"Seed":1,"IngestInfo":"F96F4F25CECFCD6F19912B2A62FA3224","pm_patch_variations":[null,null],"Masks":{"What":"Mask/Paint","MaskActive":true,"MaskBlendMode":0,"MaskInverted":false,"MaskSyncID":"19943B306810B248848CD2D4979F16F5","MaskValue":1,"Radius":0.004107,"Flow":1,"CenterWeight":1,"Dabs":["r 0.003998","d 0.303910 0.249458"]}},{"SpotType":"heal_patchmatch","SourceState":"sourceAutoComputed","Opacity":1,"Seed":1,"IngestInfo":"4706A2798C60FC96AF8A65022159D562","pm_patch_variations":[null,null],"Masks":{"What":"Mask/Paint","MaskActive":true,"MaskBlendMode":0,"MaskInverted":false,"MaskSyncID":"85E37D5CD984EE49A86EF0091CDD2180","MaskValue":1,"Radius":0.004107,"Flow":1,"CenterWeight":1,"Dabs":["r 0.003995","d 0.296868 0.279705"]}}],"Look":{"Description":{"Name":"Vintage 10","Amount":1,"Cluster":"Adobe","UUID":"AE851798974C4DAA040845432D56E13C","SupportsMonochrome":false,"Copyright":"© 2018 Adobe Systems, Inc.","Group":{"lang":"x-default","value":"Vintage"},"Parameters":{"Description":{"Version":18.1,"ProcessVersion":15.4,"ConvertToGrayscale":false,"LookTable":"E1095149FDB39D7A057BAB208837E2E1","RGBTable":"E7797C1E60CA913A25C91DE4B9547237","PointColors":"-1.000000, -1.000000, -1.000000, -1.000000, -1.000000, -1.000000, -1.000000, -1.000000, -1.000000, -1.000000, -1.000000, -1.000000, -1.000000, -1.000000, -1.000000, -1.000000, -1.000000, -1.000000, -1.000000","ColorVariance":-50}}}},"weightedFlatSubject":["kristofz",2025],"Make":"NIKON CORPORATION","Model":"NIKON D500","XResolution":240,"YResolution":240,"ResolutionUnit":"inches","Software":"Adobe Photoshop Lightroom Classic 15.1 (Windows)","Artist":"Kristof Zerbe","Copyright":"2025","ExposureTime":0.002,"FNumber":11,"ExposureProgram":"Normal program","ISO":1250,"SensitivityType":2,"ExifVersion":"2.3.1","DateTimeOriginal":"2025-04-20T09:17:16.000Z","OffsetTime":"+01:00","ShutterSpeedValue":8.965784,"ApertureValue":6.918863,"ExposureCompensation":0,"MaxApertureValue":4.4,"MeteringMode":"Pattern","LightSource":"Unknown","Flash":"Flash did not fire","FocalLength":70,"SubSecTimeOriginal":"61","SubSecTimeDigitized":"61","ColorSpace":1,"FocalPlaneXResolution":2360.8599243164062,"FocalPlaneYResolution":2360.8599243164062,"FocalPlaneResolutionUnit":"Centimeter","SensingMethod":"One-chip color area sensor","FileSource":"Digital Camera","SceneType":"Directly photographed","CFAPattern":{"0":2,"1":0,"2":2,"3":0,"4":0,"5":1,"6":1,"7":2},"CustomRendered":"Normal","ExposureMode":"Auto","FocalLengthIn35mmFormat":105,"SceneCaptureType":"Standard","GainControl":"Low gain up","Contrast":"Normal","SubjectDistanceRange":"Unknown","GPSVersionID":"2.3.0.0","GPSLatitudeRef":"N","GPSLatitude":[50,8.4072,0],"GPSLongitudeRef":"E","GPSLongitude":[7,44.1063,0],"GPSAltitudeRef":{"0":0},"GPSAltitude":196,"GPSTimeStamp":"10:17:16","GPSSatellites":"07","GPSMapDatum":"WGS84","GPSDateStamp":"2025:04:20","latitude":50.14012,"longitude":7.735105}