{"custom":{"name":"24-12-Suedafrika-0478-D50","file":"24-12-Suedafrika-0478-D50.jpg","featured":{"title":"Hout Bay & Cape Town","url":"/post/Hout-Bay-Cape-Town"},"links":[{"site":"500px","url":""},{"site":"pixelfed","url":""},{"site":"flickr","url":""},{"site":"unsplash","url":""},{"site":"vernissage","url":""}]},"ApplicationRecordVersion":"\u0000\u0004","Keywords":["2024","Südafrika","kristofz"],"DateCreated":"2024-12-18T09:24:49.09","TimeCreated":"092449","DigitalCreationDate":"20241218","DigitalCreationTime":"092449","Byline":"Kristof Zerbe","City":"Robben Island","State":"Westkap","CountryCode":"ZA","Country":"Südafrika","CopyrightNotice":"2024","CreatorTool":"Adobe Photoshop Lightroom Classic 14.2 (Windows)","CreateDate":"2024-12-18T08:24:49.000Z","ModifyDate":"2025-03-03T16:33:51.000Z","MetadataDate":"2025-03-03T17:33:51+01:00","Rating":3,"Label":"Grün","format":"image/jpeg","creator":"Kristof Zerbe","rights":{"lang":"x-default","value":2024},"subject":[2024,"Südafrika","kristofz"],"SerialNumber":"6067053","LensInfo":[18,400,3.5,6.3],"Lens":"TAMRON 18-400mm F3.5-6.3 Di II VC HLD B028N","LensID":224,"ImageNumber":21726,"ApproximateFocusDistance":"4294967295/1","DistortionCorrectionAlreadyApplied":true,"LateralChromaticAberrationCorrectionAlreadyApplied":true,"VignetteCorrectionAlreadyApplied":true,"LensModel":"TAMRON 18-400mm F3.5-6.3 Di II VC HLD B028N","DocumentID":"xmp.did:56a129cb-5f16-7949-add0-372c1cb4378d","PreservedFileName":"24-12-Südafrika-0478-D50.NEF","OriginalDocumentID":"5EB734D05EC0DD4413835B62A55F78D4","InstanceID":"xmp.iid:56a129cb-5f16-7949-add0-372c1cb4378d","History":[{"action":"derived","parameters":"converted from image/x-nikon-nef to image/jpeg, saved to new location"},{"action":"saved","instanceID":"xmp.iid:56a129cb-5f16-7949-add0-372c1cb4378d","when":"2025-03-03T17:33:51+01:00","softwareAgent":"Adobe Photoshop Lightroom Classic 14.2 (Windows)","changed":"/"}],"DerivedFrom":{"documentID":"5EB734D05EC0DD4413835B62A55F78D4","originalDocumentID":"5EB734D05EC0DD4413835B62A55F78D4"},"Marked":true,"pick":0,"CreatorContactInfo":{"CiAdrCity":"Wiesbaden","CiUrlWork":"https://kiko.io"},"RawFileName":"24-12-Südafrika-0478-D50.NEF","Version":17.2,"ProcessVersion":15.4,"WhiteBalance":"Auto","Temperature":5453,"Tint":29,"Exposure2012":0.74,"Contrast2012":20,"Highlights2012":-100,"Shadows2012":81,"Whites2012":78,"Blacks2012":-43,"Texture":40,"Clarity2012":9,"Dehaze":61,"ParametricShadows":0,"ParametricDarks":0,"ParametricLights":0,"ParametricHighlights":0,"ParametricShadowSplit":25,"ParametricMidtoneSplit":50,"ParametricHighlightSplit":75,"Sharpness":"Normal","SharpenRadius":1.8,"SharpenDetail":25,"SharpenEdgeMasking":0,"LuminanceSmoothing":71,"LuminanceNoiseReductionDetail":39,"LuminanceNoiseReductionContrast":0,"ColorNoiseReduction":25,"ColorNoiseReductionDetail":50,"ColorNoiseReductionSmoothness":50,"GrayMixerRed":0,"GrayMixerOrange":0,"GrayMixerYellow":0,"GrayMixerGreen":0,"GrayMixerAqua":0,"GrayMixerBlue":0,"GrayMixerPurple":0,"GrayMixerMagenta":0,"SplitToningShadowHue":0,"SplitToningShadowSaturation":0,"SplitToningHighlightHue":0,"SplitToningHighlightSaturation":0,"SplitToningBalance":0,"ColorGradeMidtoneHue":0,"ColorGradeMidtoneSat":0,"ColorGradeShadowLum":0,"ColorGradeMidtoneLum":0,"ColorGradeHighlightLum":0,"ColorGradeBlending":50,"ColorGradeGlobalHue":0,"ColorGradeGlobalSat":0,"ColorGradeGlobalLum":0,"AutoLateralCA":1,"LensProfileEnable":1,"LensManualDistortionAmount":0,"VignetteAmount":0,"PerspectiveUpright":0,"PerspectiveVertical":0,"PerspectiveHorizontal":0,"PerspectiveRotate":0,"PerspectiveAspect":0,"PerspectiveScale":100,"PerspectiveX":0,"PerspectiveY":0,"GrainAmount":0,"PostCropVignetteAmount":-43,"PostCropVignetteMidpoint":50,"PostCropVignetteFeather":50,"PostCropVignetteRoundness":0,"PostCropVignetteStyle":1,"PostCropVignetteHighlightContrast":0,"ShadowTint":0,"RedHue":0,"RedSaturation":0,"GreenHue":0,"GreenSaturation":0,"BlueHue":0,"BlueSaturation":0,"HDREditMode":0,"OverrideLookVignette":true,"ToneCurveName2012":"Linear","CameraProfile":"Adobe Standard","CameraProfileDigest":"ABB0410514417CFA55F22BBA7035E8AB","LensProfileSetup":"LensDefaults","LensProfileName":"Adobe (TAMRON 18-400mm F3.5-6.3 Di II VC HLD B028N, NIKON CORPORATION)","LensProfileFilename":"NIKON CORPORATION (TAMRON 18-400mm F3.5-6.3 DiII VC HLD B028N) - RAW.lcp","LensProfileDigest":"D225EFB6E890637B304B00CCCC1E2448","LensProfileIsEmbedded":false,"LensProfileDistortionScale":100,"LensProfileVignettingScale":100,"ToggleStyleDigest":"B5217C8386FEFBEB46D41DB1B1AFF8EC","ToggleStyleAmount":1,"HasSettings":true,"CropTop":0.009851,"CropLeft":0.002736,"CropBottom":0.990149,"CropRight":0.997264,"CropAngle":-0.38,"CropConstrainToWarp":1,"HasCrop":true,"AlreadyApplied":true,"ToneCurvePV2012":["0, 0","255, 255"],"ToneCurvePV2012Red":["0, 0","255, 255"],"ToneCurvePV2012Green":["0, 0","255, 255"],"ToneCurvePV2012Blue":["0, 0","255, 255"],"PointColors":"-1.000000, -1.000000, -1.000000, -1.000000, -1.000000, -1.000000, -1.000000, -1.000000, -1.000000, -1.000000, -1.000000, -1.000000, -1.000000, -1.000000, -1.000000, -1.000000, -1.000000, -1.000000, -1.000000","Look":{"Description":{"Name":"Adobe Monochrome","Amount":1,"UUID":"0CFE8F8AB5F63B2A73CE0B0077D20817","SupportsAmount":false,"SupportsMonochrome":false,"SupportsOutputReferred":false,"Copyright":"© 2018 Adobe Systems, Inc.","Group":{"lang":"x-default","value":"Profiles"},"Parameters":{"Description":{"Version":17.2,"ProcessVersion":15.4,"Clarity2012":8,"ConvertToGrayscale":true,"CameraProfile":"Adobe Standard","LookTable":"73ED6C18DDE909DD7EA2D771F5AC282D","ToneCurvePV2012":["0, 0","64, 56","128, 128","192, 197","255, 255"],"ToneCurvePV2012Red":["0, 0","255, 255"],"ToneCurvePV2012Green":["0, 0","255, 255"],"ToneCurvePV2012Blue":["0, 0","255, 255"]}}}},"weightedFlatSubject":["kristofz",2024,"Südafrika"],"Make":"NIKON CORPORATION","Model":"NIKON D500","XResolution":240,"YResolution":240,"ResolutionUnit":"inches","Software":"Adobe Photoshop Lightroom Classic 14.2 (Windows)","Artist":"Kristof Zerbe","Copyright":"2024","ExposureTime":0.0025,"FNumber":3.5,"ExposureProgram":"Normal program","ISO":4000,"SensitivityType":2,"ExifVersion":"2.3.1","DateTimeOriginal":"2024-12-18T08:24:49.000Z","OffsetTime":"+01:00","ShutterSpeedValue":8.643856,"ApertureValue":3.61471,"ExposureCompensation":0,"MaxApertureValue":3.6,"MeteringMode":"Pattern","LightSource":"Unknown","Flash":"Flash did not fire","FocalLength":18,"SubSecTimeOriginal":"09","SubSecTimeDigitized":"09","ColorSpace":1,"FocalPlaneXResolution":2360.8599243164062,"FocalPlaneYResolution":2360.8599243164062,"FocalPlaneResolutionUnit":"Centimeter","SensingMethod":"One-chip color area sensor","FileSource":"Digital Camera","SceneType":"Directly photographed","CFAPattern":{"0":2,"1":0,"2":2,"3":0,"4":0,"5":1,"6":1,"7":2},"CustomRendered":"Normal","ExposureMode":"Auto","FocalLengthIn35mmFormat":27,"SceneCaptureType":"Standard","GainControl":"High gain up","Contrast":"Normal","Saturation":"Normal","SubjectDistanceRange":"Unknown","GPSVersionID":"2.3.0.0","GPSLatitudeRef":"S","GPSLatitude":[33,48.0171,0],"GPSLongitudeRef":"E","GPSLongitude":[18,22.2511,0],"GPSAltitudeRef":{"0":0},"GPSAltitude":7,"GPSTimeStamp":"8:24:49","GPSSatellites":"11","GPSMapDatum":"WGS84","GPSDateStamp":"2024:12:18","latitude":-33.800285,"longitude":18.370851666666667}