{"custom":{"name":"24-12-Suedafrika-3542-D70","file":"24-12-Suedafrika-3542-D70.jpg","featured":{"title":"Schotia Safaris Private Game Reserve","url":"/post/Schotia-Safaris-Private-Game-Reserve"},"links":[{"site":"500px","url":""},{"site":"pixelfed","url":""},{"site":"flickr","url":""},{"site":"unsplash","url":""},{"site":"vernissage","url":""}]},"ApplicationRecordVersion":"\u0000\u0004","Keywords":["2024","Südafrika","kristofz"],"DateCreated":"2025-01-02T15:19:19.90","TimeCreated":"151919","DigitalCreationDate":"20250102","DigitalCreationTime":"151919","Byline":"Kristof Zerbe","City":"Sunday's River Valley","State":"Ostkap","CountryCode":"ZA","Country":"Südafrika","CopyrightNotice":"2024","CreatorTool":"Adobe Photoshop Lightroom Classic 14.1.1 (Windows)","ModifyDate":"2025-02-11T07:59:46.000Z","CreateDate":"2025-01-02T14:19:19.000Z","MetadataDate":"2025-02-11T08:59:46+01:00","Rating":4,"Label":"Grün","SerialNumber":"6030956","LensInfo":[150,600,5,6.3],"Lens":"150.0-600.0 mm f/5.0-6.3","LensID":227,"ImageNumber":31074,"ApproximateFocusDistance":"631/10","LateralChromaticAberrationCorrectionAlreadyApplied":true,"DocumentID":"xmp.did:1da70471-5bbc-f34a-9a60-183f00fe4c10","PreservedFileName":"24-12-Südafrika-3542-D70.NEF","OriginalDocumentID":"475BF5E083A7967BA5826267D89C816C","InstanceID":"xmp.iid:1da70471-5bbc-f34a-9a60-183f00fe4c10","History":[{"action":"derived","parameters":"converted from image/x-nikon-nef to image/jpeg, saved to new location"},{"action":"saved","instanceID":"xmp.iid:1da70471-5bbc-f34a-9a60-183f00fe4c10","when":"2025-02-11T08:59:46+01:00","softwareAgent":"Adobe Photoshop Lightroom Classic 14.1.1 (Windows)","changed":"/"}],"DerivedFrom":{"documentID":"475BF5E083A7967BA5826267D89C816C","originalDocumentID":"475BF5E083A7967BA5826267D89C816C"},"format":"image/jpeg","creator":"Kristof Zerbe","rights":{"lang":"x-default","value":2024},"subject":[2024,"Südafrika","kristofz"],"Marked":true,"pick":0,"CreatorContactInfo":{"CiAdrCity":"Wiesbaden","CiUrlWork":"https://kiko.io"},"RawFileName":"24-12-Südafrika-3542-D70.NEF","Version":17.1,"CompatibleVersion":234881024,"ProcessVersion":15.4,"WhiteBalance":"Auto","Temperature":5094,"Tint":21,"Exposure2012":0.52,"Contrast2012":-26,"Highlights2012":-95,"Shadows2012":88,"Whites2012":53,"Blacks2012":-18,"Texture":40,"Clarity2012":26,"Dehaze":65,"Vibrance":36,"Saturation":"Normal","ParametricShadows":0,"ParametricDarks":0,"ParametricLights":0,"ParametricHighlights":0,"ParametricShadowSplit":25,"ParametricMidtoneSplit":50,"ParametricHighlightSplit":75,"Sharpness":"Normal","SharpenRadius":1.8,"SharpenDetail":25,"SharpenEdgeMasking":0,"LuminanceSmoothing":88,"LuminanceNoiseReductionDetail":38,"LuminanceNoiseReductionContrast":0,"ColorNoiseReduction":25,"ColorNoiseReductionDetail":50,"ColorNoiseReductionSmoothness":50,"HueAdjustmentRed":0,"HueAdjustmentOrange":0,"HueAdjustmentYellow":0,"HueAdjustmentGreen":0,"HueAdjustmentAqua":0,"HueAdjustmentBlue":0,"HueAdjustmentPurple":0,"HueAdjustmentMagenta":0,"SaturationAdjustmentRed":0,"SaturationAdjustmentOrange":0,"SaturationAdjustmentYellow":-19,"SaturationAdjustmentGreen":0,"SaturationAdjustmentAqua":3,"SaturationAdjustmentBlue":0,"SaturationAdjustmentPurple":0,"SaturationAdjustmentMagenta":0,"LuminanceAdjustmentRed":0,"LuminanceAdjustmentOrange":-4,"LuminanceAdjustmentYellow":-13,"LuminanceAdjustmentGreen":0,"LuminanceAdjustmentAqua":0,"LuminanceAdjustmentBlue":-14,"LuminanceAdjustmentPurple":0,"LuminanceAdjustmentMagenta":0,"SplitToningShadowHue":0,"SplitToningShadowSaturation":0,"SplitToningHighlightHue":0,"SplitToningHighlightSaturation":0,"SplitToningBalance":0,"ColorGradeMidtoneHue":0,"ColorGradeMidtoneSat":0,"ColorGradeShadowLum":0,"ColorGradeMidtoneLum":0,"ColorGradeHighlightLum":0,"ColorGradeBlending":50,"ColorGradeGlobalHue":0,"ColorGradeGlobalSat":0,"ColorGradeGlobalLum":0,"AutoLateralCA":1,"LensProfileEnable":1,"LensManualDistortionAmount":0,"VignetteAmount":0,"DefringePurpleAmount":0,"DefringePurpleHueLo":30,"DefringePurpleHueHi":70,"DefringeGreenAmount":0,"DefringeGreenHueLo":40,"DefringeGreenHueHi":60,"PerspectiveUpright":0,"PerspectiveVertical":0,"PerspectiveHorizontal":0,"PerspectiveRotate":0,"PerspectiveAspect":0,"PerspectiveScale":100,"PerspectiveX":0,"PerspectiveY":0,"GrainAmount":0,"PostCropVignetteAmount":-38,"PostCropVignetteMidpoint":50,"PostCropVignetteFeather":50,"PostCropVignetteRoundness":0,"PostCropVignetteStyle":1,"PostCropVignetteHighlightContrast":0,"ShadowTint":0,"RedHue":0,"RedSaturation":0,"GreenHue":0,"GreenSaturation":0,"BlueHue":0,"BlueSaturation":0,"HDREditMode":0,"ConvertToGrayscale":false,"OverrideLookVignette":true,"ToneCurveName2012":"Linear","CameraProfile":"Adobe Standard","CameraProfileDigest":"2FEA3EA92D5DFE77FBB77CCAD84C4769","LensProfileSetup":"LensDefaults","HasSettings":true,"CropTop":0.114041,"CropLeft":0,"CropBottom":1,"CropRight":0.874469,"CropAngle":0,"CropConstrainToWarp":1,"HasCrop":true,"AlreadyApplied":true,"ToneCurvePV2012":["0, 0","255, 255"],"ToneCurvePV2012Red":["0, 0","255, 255"],"ToneCurvePV2012Green":["0, 0","255, 255"],"ToneCurvePV2012Blue":["0, 0","255, 255"],"PointColors":"-1.000000, -1.000000, -1.000000, -1.000000, -1.000000, -1.000000, -1.000000, -1.000000, -1.000000, -1.000000, -1.000000, -1.000000, -1.000000, -1.000000, -1.000000, -1.000000, -1.000000, -1.000000, -1.000000","MaskGroupBasedCorrections":{"What":"Correction","CorrectionAmount":1,"CorrectionActive":true,"CorrectionName":"Mask 1","CorrectionSyncID":"CE15979E7BADD64CA7CC74C67800260B","LocalExposure":0,"LocalHue":0,"LocalSaturation":0,"LocalContrast":0,"LocalClarity":0,"LocalSharpness":0,"LocalBrightness":0,"LocalToningHue":0,"LocalToningSaturation":0,"LocalExposure2012":0.21825,"LocalContrast2012":0,"LocalHighlights2012":0,"LocalShadows2012":0,"LocalWhites2012":0,"LocalBlacks2012":0,"LocalClarity2012":0,"LocalDehaze":0,"LocalLuminanceNoise":0,"LocalMoire":0,"LocalDefringe":0,"LocalTemperature":0,"LocalTint":0,"LocalTexture":0,"LocalGrain":0,"LocalCurveRefineSaturation":100,"CorrectionMasks":{"What":"Mask/Aggregate","MaskActive":true,"MaskName":"Brush 1","MaskBlendMode":0,"MaskInverted":false,"MaskSyncID":"C0B224341981E544A42FF130B8041A2B","MaskValue":1,"Masks":{"What":"Mask/Paint","MaskActive":true,"MaskBlendMode":0,"MaskInverted":false,"MaskSyncID":"6D43EFA72A888D4EABB53AF05DC98607","MaskValue":1,"Radius":0.032243,"Flow":0.8,"CenterWeight":0.16214,"Dabs":["f 0.8000","h 0.1621","d 0.547100 0.428872","d 0.537572 0.426354","d 0.528036 0.423966","d 0.523056 0.435423","d 0.520068 0.449289","d 0.516224 0.462686","d 0.512007 0.475804","d 0.508096 0.488999","d 0.507055 0.503491","d 0.505800 0.517908","d 0.504589 0.532349","d 0.502127 0.546427","d 0.498113 0.559631","d 0.492766 0.571637","d 0.483739 0.574857","d 0.474070 0.575262","d 0.464398 0.575333","d 0.454725 0.575333","d 0.445053 0.575287","d 0.435405 0.574247","d 0.425934 0.574776","d 0.416272 0.575436","d 0.406603 0.575872","d 0.396935 0.576308","d 0.387266 0.576726","d 0.377597 0.576342","d 0.367927 0.576034","d 0.358910 0.579269","d 0.349328 0.581067","d 0.339718 0.582682","d 0.330324 0.585144","d 0.320661 0.585738","d 0.311000 0.586468","d 0.301343 0.586833","d 0.291866 0.589589","d 0.282580 0.593431","d 0.272985 0.594954","d 0.263900 0.598942","d 0.263399 0.601261","d 0.273023 0.602391","d 0.282369 0.606060","d 0.291721 0.609786","d 0.301280 0.611588","d 0.310739 0.613519","d 0.320176 0.616675","d 0.329831 0.617552","d 0.339487 0.618427","d 0.349139 0.619380","d 0.358781 0.619857","d 0.368395 0.618244","d 0.377804 0.614960","d 0.387222 0.611835","d 0.396813 0.610592","d 0.406480 0.610138","d 0.416150 0.609764","d 0.425811 0.610279","d 0.435403 0.611979","d 0.444967 0.613875","d 0.454640 0.613875","d 0.452671 0.614576","d 0.443002 0.614873","d 0.433339 0.615537","d 0.423684 0.616384","d 0.414045 0.617597","d 0.404406 0.618810","d 0.394789 0.620344","d 0.385234 0.622579","d 0.375772 0.625597","d 0.366154 0.626489","d 0.356481 0.626489","d 0.346842 0.627640"]}}},"weightedFlatSubject":["kristofz",2024,"Südafrika"],"Make":"NIKON CORPORATION","Model":"NIKON D7000","XResolution":240,"YResolution":240,"ResolutionUnit":"inches","Software":"Adobe Photoshop Lightroom Classic 14.1.1 (Windows)","Artist":"Kristof Zerbe","Copyright":"2024","ExposureTime":0.0004,"FNumber":6.3,"ExposureProgram":"Normal program","ISO":1250,"SensitivityType":2,"ExifVersion":"2.3.1","DateTimeOriginal":"2025-01-02T14:19:19.000Z","OffsetTime":"+01:00","ShutterSpeedValue":11.287712,"ApertureValue":5.310704,"ExposureCompensation":0,"MaxApertureValue":5.3,"MeteringMode":"Pattern","LightSource":"Unknown","Flash":"Flash did not fire, compulsory flash mode","FocalLength":460,"SubSecTimeOriginal":"90","SubSecTimeDigitized":"90","ColorSpace":1,"SensingMethod":"One-chip color area sensor","FileSource":"Digital Camera","SceneType":"Directly photographed","CFAPattern":{"0":2,"1":0,"2":2,"3":0,"4":0,"5":1,"6":1,"7":2},"CustomRendered":"Normal","ExposureMode":"Auto","DigitalZoomRatio":1,"FocalLengthIn35mmFormat":690,"SceneCaptureType":"Standard","GainControl":"High gain up","Contrast":"Normal","SubjectDistanceRange":"Unknown","LensModel":"150.0-600.0 mm f/5.0-6.3","GPSVersionID":"2.2.0.0","GPSLatitudeRef":"S","GPSLatitude":[33,32.9845,0],"GPSLongitudeRef":"E","GPSLongitude":[25,50.584,0],"latitude":-33.54974166666667,"longitude":25.843066666666665}