{"custom":{"name":"23-09-11 Speyer-0029","file":"23-09-11 Speyer-0029.jpg","links":[{"site":"500px","url":""},{"site":"pixelfed","url":""}]},"ApplicationRecordVersion":"\u0000\u0004","ObjectName":"Red Motor Cover","Keywords":["2023","Speyer","kristofz"],"DateCreated":"2023-09-11T10:42:01.40","TimeCreated":"104201","DigitalCreationDate":"20230911","DigitalCreationTime":"104201","Byline":"Kristof Zerbe","City":"Speyer","State":"Rhineland-Palatinate","CountryCode":"DE","Country":"Germany","CopyrightNotice":"2023","CreatorTool":"Adobe Photoshop Lightroom Classic 12.5 (Windows)","CreateDate":"2023-09-11T08:42:01.000Z","ModifyDate":"2023-11-15T14:57:42.000Z","MetadataDate":"2023-11-15T15:57:42+01:00","Rating":3,"Label":"Green","format":"image/jpeg","creator":"Kristof Zerbe","title":{"lang":"x-default","value":"Red Motor Cover"},"rights":{"lang":"x-default","value":2023},"subject":[2023,"Speyer","kristofz"],"SerialNumber":"6067053","LensInfo":[18,400,3.5,6.3],"Lens":"TAMRON 18-400mm F3.5-6.3 Di II VC HLD B028N","LensID":224,"ImageNumber":15761,"ApproximateFocusDistance":"4294967295/1","DistortionCorrectionAlreadyApplied":true,"LateralChromaticAberrationCorrectionAlreadyApplied":true,"VignetteCorrectionAlreadyApplied":true,"LensModel":"TAMRON 18-400mm F3.5-6.3 Di II VC HLD B028N","DocumentID":"xmp.did:613a5191-02df-8c41-97a8-78d13d6cf834","PreservedFileName":"D50_5657.NEF","OriginalDocumentID":"0072E69FA2D5169C767E0EEB3801ECC1","InstanceID":"xmp.iid:613a5191-02df-8c41-97a8-78d13d6cf834","History":[{"action":"derived","parameters":"converted from image/x-nikon-nef to image/jpeg, saved to new location"},{"action":"saved","instanceID":"xmp.iid:613a5191-02df-8c41-97a8-78d13d6cf834","when":"2023-11-15T15:57:42+01:00","softwareAgent":"Adobe Photoshop Lightroom Classic 12.5 (Windows)","changed":"/"}],"DerivedFrom":{"documentID":"0072E69FA2D5169C767E0EEB3801ECC1","originalDocumentID":"0072E69FA2D5169C767E0EEB3801ECC1"},"Marked":true,"CreatorContactInfo":{"CiAdrCtry":"Germany","CiAdrCity":"Wiesbaden"},"RawFileName":"23-09-11 Speyer-0029.NEF","Version":15.5,"ProcessVersion":15.4,"WhiteBalance":"Auto","Temperature":4150,"Tint":10,"Exposure2012":0.26,"Contrast2012":-34,"Highlights2012":-88,"Shadows2012":86,"Whites2012":-44,"Blacks2012":56,"Texture":45,"Clarity2012":68,"Dehaze":85,"Vibrance":51,"Saturation":"Normal","ParametricShadows":0,"ParametricDarks":0,"ParametricLights":0,"ParametricHighlights":0,"ParametricShadowSplit":25,"ParametricMidtoneSplit":50,"ParametricHighlightSplit":75,"Sharpness":"Normal","SharpenRadius":1,"SharpenDetail":15,"SharpenEdgeMasking":43,"LuminanceSmoothing":82,"LuminanceNoiseReductionDetail":50,"LuminanceNoiseReductionContrast":0,"ColorNoiseReduction":25,"ColorNoiseReductionDetail":50,"ColorNoiseReductionSmoothness":50,"HueAdjustmentRed":0,"HueAdjustmentOrange":0,"HueAdjustmentYellow":0,"HueAdjustmentGreen":0,"HueAdjustmentAqua":0,"HueAdjustmentBlue":0,"HueAdjustmentPurple":0,"HueAdjustmentMagenta":0,"SaturationAdjustmentRed":39,"SaturationAdjustmentOrange":25,"SaturationAdjustmentYellow":0,"SaturationAdjustmentGreen":0,"SaturationAdjustmentAqua":0,"SaturationAdjustmentBlue":-23,"SaturationAdjustmentPurple":0,"SaturationAdjustmentMagenta":0,"LuminanceAdjustmentRed":0,"LuminanceAdjustmentOrange":0,"LuminanceAdjustmentYellow":0,"LuminanceAdjustmentGreen":0,"LuminanceAdjustmentAqua":0,"LuminanceAdjustmentBlue":10,"LuminanceAdjustmentPurple":0,"LuminanceAdjustmentMagenta":0,"SplitToningShadowHue":0,"SplitToningShadowSaturation":0,"SplitToningHighlightHue":0,"SplitToningHighlightSaturation":0,"SplitToningBalance":0,"ColorGradeMidtoneHue":0,"ColorGradeMidtoneSat":0,"ColorGradeShadowLum":0,"ColorGradeMidtoneLum":0,"ColorGradeHighlightLum":0,"ColorGradeBlending":50,"ColorGradeGlobalHue":0,"ColorGradeGlobalSat":0,"ColorGradeGlobalLum":0,"AutoLateralCA":1,"LensProfileEnable":1,"LensManualDistortionAmount":0,"VignetteAmount":0,"DefringePurpleAmount":0,"DefringePurpleHueLo":30,"DefringePurpleHueHi":70,"DefringeGreenAmount":0,"DefringeGreenHueLo":40,"DefringeGreenHueHi":60,"PerspectiveUpright":0,"PerspectiveVertical":9,"PerspectiveHorizontal":9,"PerspectiveRotate":-0.7,"PerspectiveAspect":0,"PerspectiveScale":100,"PerspectiveX":0,"PerspectiveY":0,"GrainAmount":0,"PostCropVignetteAmount":0,"ShadowTint":0,"RedHue":0,"RedSaturation":0,"GreenHue":0,"GreenSaturation":0,"BlueHue":0,"BlueSaturation":0,"CurveRefineSaturation":100,"ConvertToGrayscale":false,"OverrideLookVignette":true,"ToneCurveName2012":"Custom","CameraProfile":"Adobe Standard","CameraProfileDigest":"ABB0410514417CFA55F22BBA7035E8AB","LensProfileSetup":"LensDefaults","LensProfileName":"Adobe (TAMRON 18-400mm F3.5-6.3 Di II VC HLD B028N, NIKON CORPORATION)","LensProfileFilename":"NIKON CORPORATION (TAMRON 18-400mm F3.5-6.3 DiII VC HLD B028N) - RAW.lcp","LensProfileDigest":"D225EFB6E890637B304B00CCCC1E2448","LensProfileIsEmbedded":false,"LensProfileDistortionScale":100,"LensProfileVignettingScale":100,"HasSettings":true,"CropTop":0.049043,"CropLeft":0.073713,"CropBottom":0.980173,"CropRight":0.998212,"CropAngle":0,"CropConstrainToWarp":1,"HasCrop":true,"AlreadyApplied":true,"ToneCurvePV2012":["0, 0","75, 65","127, 127","183, 199","255, 255"],"ToneCurvePV2012Red":["0, 0","255, 255"],"ToneCurvePV2012Green":["10, 0","255, 255"],"ToneCurvePV2012Blue":["0, 0","139, 118","255, 255"],"weightedFlatSubject":[2023,"kristofz","Speyer"],"Make":"NIKON CORPORATION","Model":"NIKON D500","XResolution":240,"YResolution":240,"ResolutionUnit":"inches","Software":"Adobe Photoshop Lightroom Classic 12.5 (Windows)","Artist":"Kristof Zerbe","Copyright":"2023","ExposureTime":0.0025,"FNumber":5.6,"ExposureProgram":"Normal program","ISO":4000,"SensitivityType":2,"ExifVersion":"2.3.1","DateTimeOriginal":"2023-09-11T08:42:01.000Z","OffsetTime":"+01:00","ShutterSpeedValue":8.643856,"ApertureValue":4.970854,"ExposureCompensation":0,"MaxApertureValue":5,"MeteringMode":"Pattern","LightSource":"Unknown","Flash":"Flash did not fire","FocalLength":145,"SubSecTimeOriginal":"40","SubSecTimeDigitized":"40","ColorSpace":1,"FocalPlaneXResolution":2360.8599243164062,"FocalPlaneYResolution":2360.8599243164062,"FocalPlaneResolutionUnit":"Centimeter","SensingMethod":"One-chip color area sensor","FileSource":"Digital Camera","SceneType":"Directly photographed","CFAPattern":{"0":2,"1":0,"2":2,"3":0,"4":0,"5":1,"6":1,"7":2},"CustomRendered":"Normal","ExposureMode":"Auto","FocalLengthIn35mmFormat":217,"SceneCaptureType":"Standard","GainControl":"High gain up","Contrast":"Normal","SubjectDistanceRange":"Unknown","GPSVersionID":"2.2.0.0","GPSLatitudeRef":"N","GPSLatitude":[49,18.6882518,0],"GPSLongitudeRef":"E","GPSLongitude":[8,26.8295596,0],"latitude":49.311470863333334,"longitude":8.447159326666666}